m3_django_compatibility/__init__.py
m3_django_compatibility/exceptions.py
m3_django_compatibility/middleware.py
m3_django_compatibility/models.py
m3_django_compatibility-1.12.0.dist-info/licenses/LICENSE
tests/__init__.py
tests/manage.py
tests/settings.py
tests/myapp/__init__.py
tests/myapp/models.py
tests/myapp/tests.py
tests/myapp/urls.py
tests/myapp/views.py
tests/myapp/management/__init__.py
tests/myapp/management/commands/__init__.py
tests/myapp/management/commands/test_command.py
tests/user/__init__.py
tests/user/models.py
m3_django_compatibility-1.12.0.dist-info/METADATA
m3_django_compatibility-1.12.0.dist-info/WHEEL
m3_django_compatibility-1.12.0.dist-info/top_level.txt
m3_django_compatibility-1.12.0.dist-info/RECORD
